position_encoding/__init__.py
position_encoding/absolute.py
position_encoding/relative.py
position_encoding-1.0.0.dist-info/licenses/LICENSE
position_encoding-1.0.0.dist-info/licenses/NOTICE
position_encoding-1.0.0.dist-info/METADATA
position_encoding-1.0.0.dist-info/WHEEL
position_encoding-1.0.0.dist-info/top_level.txt
position_encoding-1.0.0.dist-info/RECORD
